haystack_integrations/components/retrievers/py.typed
haystack_integrations/components/retrievers/weaviate/__init__.py
haystack_integrations/components/retrievers/weaviate/bm25_retriever.py
haystack_integrations/components/retrievers/weaviate/embedding_retriever.py
haystack_integrations/components/retrievers/weaviate/hybrid_retriever.py
haystack_integrations/document_stores/py.typed
haystack_integrations/document_stores/weaviate/__init__.py
haystack_integrations/document_stores/weaviate/_filters.py
haystack_integrations/document_stores/weaviate/auth.py
haystack_integrations/document_stores/weaviate/document_store.py
weaviate_haystack-7.0.0.dist-info/METADATA
weaviate_haystack-7.0.0.dist-info/WHEEL
weaviate_haystack-7.0.0.dist-info/licenses/LICENSE.txt
weaviate_haystack-7.0.0.dist-info/RECORD
